{
  "$schema": "https://developer.microsoft.com/json-schemas/fabric/item/report/definition/visualContainer/2.5.0/schema.json",
  "name": "a853d2bebfe2dd2229ab",
  "position": {
    "x": 18.333333333333336,
    "y": 607.5,
    "z": 2000,
    "height": 33.333333333333336,
    "width": 280,
    "tabOrder": 2000
  },
  "visual": {
    "visualType": "textbox",
    "objects": {
      "general": [
        {
          "properties": {
            "paragraphs": [
              {
                "textRuns": [
                  {
                    "value": "Randa Asim",
                    "textStyle": {
                      "fontWeight": "bold",
                      "fontSize": "16pt",
                      "color": "#ffffff"
                    }
                  }
                ]
              }
            ]
          }
        }
      ]
    },
    "visualContainerObjects": {
      "background": [
        {
          "properties": {
            "show": {
              "expr": {
                "Literal": {
                  "Value": "false"
                }
              }
            }
          }
        }
      ]
    },
    "drillFilterOtherVisuals": true
  }
}